bqqtest/__init__.py
bqqtest/table.py
bqqtest/table_test.py
bqqtest/testdata/test1.csv
bqqtest/testdata/test2.json
bqqtest/testdata/test3.json
bqqtest/testdata/test4.json
bqqtest/testdata/test5.json
bqqtest/util.py
bqqtest/util_test.py
bqqtest-0.6.0.dist-info/LICENSE
bqqtest-0.6.0.dist-info/WHEEL
bqqtest-0.6.0.dist-info/METADATA
bqqtest-0.6.0.dist-info/RECORD
